gowerline
