Metadata-Version: 2.1
Name: gowerline
Version: 0.0.13
Summary: Write your powerline segments in Go !
Home-page: https://github.com/thomas-maurice/gowerline
Author: Thomas Maurice
Author-email: thomas@maurice.fr
License: UNKNOWN
Platform: UNKNOWN
Classifier: Development Status :: 4 - Beta
Classifier: Environment :: Console
Classifier: Intended Audience :: Developers
Classifier: Intended Audience :: System Administrators
Classifier: Intended Audience :: End Users/Desktop
Classifier: License :: OSI Approved :: MIT License
Classifier: Operating System :: POSIX
Classifier: Programming Language :: Python :: 3.7
Classifier: Programming Language :: Python :: 3 :: Only
Classifier: Topic :: Utilities
Classifier: Topic :: System :: Shells
License-File: LICENSE
